README.rst
camtones
setup.py
camtones/__init__.py
camtones/__main__.py
camtones.egg-info/PKG-INFO
camtones.egg-info/SOURCES.txt
camtones.egg-info/dependency_links.txt
camtones.egg-info/requires.txt
camtones.egg-info/top_level.txt
camtones/haars/haarcascade_eye.xml
camtones/haars/haarcascade_eye_tree_eyeglasses.xml
camtones/haars/haarcascade_frontalcatface.xml
camtones/haars/haarcascade_frontalcatface_extended.xml
camtones/haars/haarcascade_frontalface_alt.xml
camtones/haars/haarcascade_frontalface_alt2.xml
camtones/haars/haarcascade_frontalface_alt_tree.xml
camtones/haars/haarcascade_frontalface_default.xml
camtones/haars/haarcascade_fullbody.xml
camtones/haars/haarcascade_lefteye_2splits.xml
camtones/haars/haarcascade_licence_plate_rus_16stages.xml
camtones/haars/haarcascade_lowerbody.xml
camtones/haars/haarcascade_profileface.xml
camtones/haars/haarcascade_righteye_2splits.xml
camtones/haars/haarcascade_russian_plate_number.xml
camtones/haars/haarcascade_smile.xml
camtones/haars/haarcascade_upperbody.xml
camtones/ocv/__init__.py
camtones/ocv/api.py
camtones/ocv/background_subtractors.py
camtones/ocv/cameras.py
camtones/ocv/contours.py
camtones/ocv/exceptions.py
camtones/ocv/face_extractors.py
camtones/ocv/frames.py
camtones/ocv/video_writers.py
camtones/ocv/windows.py
camtones/procs/__init__.py
camtones/procs/face.py
camtones/procs/gui.glade
camtones/procs/motion.py
scripts/camtones