Metadata-Version: 1.1
Name: camtones
Version: 0.0.2
Summary: Camera To Not-Empty Sequence is a motion and face extration system
Home-page: https://github.com/jespino/camtones
Author: Jesús Espino
Author-email: jespinog@gmail.com
License: BSD
Platform: UNKNOWN
Classifier: Programming Language :: Python :: 2.7
Classifier: Programming Language :: Python :: 3.0
Classifier: Programming Language :: Python :: 3.1
Classifier: Programming Language :: Python :: 3.2
Classifier: Programming Language :: Python :: 3.3
Classifier: Programming Language :: Python :: 3.4
Classifier: Programming Language :: Python :: 3.4
Classifier: Development Status :: 4 - Beta
Classifier: Environment :: Console
Classifier: License :: OSI Approved :: BSD License
Classifier: Operating System :: Unix
